{
	"Version": 3,
	"Meta": {
		"PhysicsSettingCount": 3,
		"TotalInputCount": 6,
		"TotalOutputCount": 5,
		"VertexCount": 6,
		"EffectiveForces": {
			"Gravity": {
				"X": 0,
				"Y": -1
			},
			"Wind": {
				"X": 0,
				"Y": 0
			}
		},
		"PhysicsDictionary": [
			{
				"Id": "PhysicsSetting1",
				"Name": "前髪揺れ"
			},
			{
				"Id": "PhysicsSetting2",
				"Name": "横髪揺れ"
			},
			{
				"Id": "PhysicsSetting3",
				"Name": "ツインテ揺れ"
			}
		]
	},
	"PhysicsSettings": [
		{
			"Id": "PhysicsSetting1",
			"Input": [
				{
					"Source": {
						"Target": "Parameter",
						"Id": "ParamAngleX"
					},
					"Weight": 60,
					"Type": "X",
					"Reflect": false
				},
				{
					"Source": {
						"Target": "Parameter",
						"Id": "ParamAngleZ"
					},
					"Weight": 60,
					"Type": "Angle",
					"Reflect": false
				}
			],
			"Output": [
				{
					"Destination": {
						"Target": "Parameter",
						"Id": "ParamKamiyureFront"
					},
					"VertexIndex": 1,
					"Scale": 2,
					"Weight": 100,
					"Type": "Angle",
					"Reflect": false
				}
			],
			"Vertices": [
				{
					"Position": {
						"X": 0,
						"Y": 0
					},
					"Mobility": 1,
					"Delay": 1,
					"Acceleration": 1,
					"Radius": 0
				},
				{
					"Position": {
						"X": 0,
						"Y": 3
					},
					"Mobility": 0.95,
					"Delay": 0.9,
					"Acceleration": 1.5,
					"Radius": 3
				}
			],
			"Normalization": {
				"Position": {
					"Minimum": -10,
					"Default": 0,
					"Maximum": 10
				},
				"Angle": {
					"Minimum": -10,
					"Default": 0,
					"Maximum": 10
				}
			}
		},
		{
			"Id": "PhysicsSetting2",
			"Input": [
				{
					"Source": {
						"Target": "Parameter",
						"Id": "ParamAngleX"
					},
					"Weight": 60,
					"Type": "X",
					"Reflect": false
				},
				{
					"Source": {
						"Target": "Parameter",
						"Id": "ParamAngleZ"
					},
					"Weight": 60,
					"Type": "Angle",
					"Reflect": false
				}
			],
			"Output": [
				{
					"Destination": {
						"Target": "Parameter",
						"Id": "ParamKamiyureSideL"
					},
					"VertexIndex": 1,
					"Scale": 1.7,
					"Weight": 100,
					"Type": "Angle",
					"Reflect": false
				},
				{
					"Destination": {
						"Target": "Parameter",
						"Id": "ParamKamiyureSideR"
					},
					"VertexIndex": 1,
					"Scale": 1.7,
					"Weight": 100,
					"Type": "Angle",
					"Reflect": false
				}
			],
			"Vertices": [
				{
					"Position": {
						"X": 0,
						"Y": 0
					},
					"Mobility": 1,
					"Delay": 1,
					"Acceleration": 1,
					"Radius": 0
				},
				{
					"Position": {
						"X": 0,
						"Y": 7.5
					},
					"Mobility": 0.95,
					"Delay": 0.8,
					"Acceleration": 1.5,
					"Radius": 7.5
				}
			],
			"Normalization": {
				"Position": {
					"Minimum": -10,
					"Default": 0,
					"Maximum": 10
				},
				"Angle": {
					"Minimum": -10,
					"Default": 0,
					"Maximum": 10
				}
			}
		},
		{
			"Id": "PhysicsSetting3",
			"Input": [
				{
					"Source": {
						"Target": "Parameter",
						"Id": "ParamAngleX"
					},
					"Weight": 60,
					"Type": "X",
					"Reflect": false
				},
				{
					"Source": {
						"Target": "Parameter",
						"Id": "ParamAngleZ"
					},
					"Weight": 60,
					"Type": "Angle",
					"Reflect": false
				}
			],
			"Output": [
				{
					"Destination": {
						"Target": "Parameter",
						"Id": "ParamKamiyureTwinL"
					},
					"VertexIndex": 1,
					"Scale": 1,
					"Weight": 100,
					"Type": "Angle",
					"Reflect": false
				},
				{
					"Destination": {
						"Target": "Parameter",
						"Id": "ParamKamiyureTwinR"
					},
					"VertexIndex": 1,
					"Scale": 1,
					"Weight": 100,
					"Type": "Angle",
					"Reflect": false
				}
			],
			"Vertices": [
				{
					"Position": {
						"X": 0,
						"Y": 0
					},
					"Mobility": 1,
					"Delay": 1,
					"Acceleration": 1,
					"Radius": 0
				},
				{
					"Position": {
						"X": 0,
						"Y": 10
					},
					"Mobility": 0.95,
					"Delay": 0.8,
					"Acceleration": 1.5,
					"Radius": 10
				}
			],
			"Normalization": {
				"Position": {
					"Minimum": -10,
					"Default": 0,
					"Maximum": 10
				},
				"Angle": {
					"Minimum": -10,
					"Default": 0,
					"Maximum": 10
				}
			}
		}
	]
}